.gitignore
CHANGES.txt
CONTRIBUTORS.txt
COPYRIGHT.txt
LICENSE.txt
README.txt
setup.cfg
setup.py
tox.ini
docs/Makefile
docs/api.rst
docs/conf.py
docs/config.rst
docs/directives.rst
docs/glossary.rst
docs/index.rst
docs/interpolation.rst
docs/.static/logo_hi.gif
docs/.static/repoze.css
repoze/__init__.py
repoze.configuration.egg-info/PKG-INFO
repoze.configuration.egg-info/SOURCES.txt
repoze.configuration.egg-info/dependency_links.txt
repoze.configuration.egg-info/entry_points.txt
repoze.configuration.egg-info/namespace_packages.txt
repoze.configuration.egg-info/not-zip-safe
repoze.configuration.egg-info/requires.txt
repoze.configuration.egg-info/top_level.txt
repoze/configuration/__init__.py
repoze/configuration/context.py
repoze/configuration/declaration.py
repoze/configuration/directives.py
repoze/configuration/exceptions.py
repoze/configuration/imperative.py
repoze/configuration/loader.py
repoze/configuration/tests/__init__.py
repoze/configuration/tests/test_api.py
repoze/configuration/tests/test_context.py
repoze/configuration/tests/test_declaration.py
repoze/configuration/tests/test_directives.py
repoze/configuration/tests/test_exceptions.py
repoze/configuration/tests/test_imperative.py
repoze/configuration/tests/test_loader.py
repoze/configuration/tests/fixtures/__init__.py
repoze/configuration/tests/fixtures/another.yml
repoze/configuration/tests/fixtures/configure.yml
repoze/configuration/tests/fixtures/conflict1.yml
repoze/configuration/tests/fixtures/conflict2.yml